[
    {
        "dcterms:creator": [],
        "dcterms:description": "A new dataset of 57k annotated utterances in English, Spanish, and Thai across the domains of weather, alarm, and reminder, designed for intent detection and slot filling tasks.",
        "dcterms:title": "Multilingual Intent and Slot Filling Dataset",
        "dcterms:issued": "",
        "dcterms:language": "English, Spanish, Thai",
        "dcterms:identifier": "https://fb.me/multilingual_task_oriented_data",
        "dcat:theme": [
            "Natural Language Processing",
            "Conversational AI"
        ],
        "dcat:keyword": [
            "Intent detection",
            "Slot filling",
            "Multilingual dataset",
            "Cross-lingual transfer learning"
        ],
        "dcat:landingPage": "https://fb.me/multilingual_task_oriented_data",
        "dcterms:hasVersion": "",
        "dcterms:format": "Text",
        "mls:task": [
            "Intent detection",
            "Slot filling"
        ]
    },
    {
        "dcterms:creator": [
            "Philipp Koehn"
        ],
        "dcterms:description": "A parallel corpus for statistical machine translation, consisting of European Parliament proceedings.",
        "dcterms:title": "Europarl v7",
        "dcterms:issued": "2005",
        "dcterms:language": "",
        "dcterms:identifier": "",
        "dcat:theme": [
            "Machine Translation"
        ],
        "dcat:keyword": [
            "Parallel corpus",
            "Statistical machine translation"
        ],
        "dcat:landingPage": "",
        "dcterms:hasVersion": "",
        "dcterms:format": "",
        "mls:task": []
    },
    {
        "dcterms:creator": [
            "Mauro Cettolo",
            "Christian Girardi",
            "Marcello Federico"
        ],
        "dcterms:description": "A dataset containing transcribed and translated talks, used for training and evaluating machine translation systems.",
        "dcterms:title": "IWSLT Training Data",
        "dcterms:issued": "2012",
        "dcterms:language": "",
        "dcterms:identifier": "",
        "dcat:theme": [
            "Machine Translation"
        ],
        "dcat:keyword": [
            "Transcribed talks",
            "Translated talks",
            "Machine translation"
        ],
        "dcat:landingPage": "",
        "dcterms:hasVersion": "",
        "dcterms:format": "",
        "mls:task": []
    },
    {
        "dcterms:creator": [
            "Pierre Lison",
            "Jörg Tiedemann",
            "Milen Kouylekov"
        ],
        "dcterms:description": "A dataset consisting of subtitles from movies and TV shows, used for statistical rescoring of sentence alignments in large, noisy parallel corpora.",
        "dcterms:title": "OpenSubtitles Data",
        "dcterms:issued": "2018",
        "dcterms:language": "",
        "dcterms:identifier": "",
        "dcat:theme": [
            "Machine Translation"
        ],
        "dcat:keyword": [
            "Subtitles",
            "Parallel corpus",
            "Statistical rescoring"
        ],
        "dcat:landingPage": "",
        "dcterms:hasVersion": "",
        "dcterms:format": "",
        "mls:task": []
    },
    {
        "dcterms:creator": [],
        "dcterms:description": "A dataset containing web-crawled parallel texts across multiple languages, used for training machine translation systems.",
        "dcterms:title": "Paracrawl Data",
        "dcterms:issued": "",
        "dcterms:language": "",
        "dcterms:identifier": "",
        "dcat:theme": [
            "Machine Translation"
        ],
        "dcat:keyword": [
            "Web-crawled data",
            "Parallel corpus"
        ],
        "dcat:landingPage": "",
        "dcterms:hasVersion": "",
        "dcterms:format": "",
        "mls:task": []
    },
    {
        "dcterms:creator": [],
        "dcterms:description": "A dataset consisting of test sets from the WMT shared tasks for machine translation, used for evaluating translation systems.",
        "dcterms:title": "newstest2008-2011",
        "dcterms:issued": "",
        "dcterms:language": "",
        "dcterms:identifier": "",
        "dcat:theme": [
            "Machine Translation"
        ],
        "dcat:keyword": [
            "Test sets",
            "Machine translation evaluation"
        ],
        "dcat:landingPage": "",
        "dcterms:hasVersion": "",
        "dcterms:format": "",
        "mls:task": []
    },
    {
        "dcterms:creator": [],
        "dcterms:description": "A dataset consisting of test sets from the WMT shared tasks for machine translation, used for evaluating translation systems.",
        "dcterms:title": "newstest2012-2013",
        "dcterms:issued": "",
        "dcterms:language": "",
        "dcterms:identifier": "",
        "dcat:theme": [
            "Machine Translation"
        ],
        "dcat:keyword": [
            "Test sets",
            "Machine translation evaluation"
        ],
        "dcat:landingPage": "",
        "dcterms:hasVersion": "",
        "dcterms:format": "",
        "mls:task": []
    },
    {
        "dcterms:creator": [],
        "dcterms:description": "A dataset containing development and test data for the IWSLT shared tasks, used for evaluating machine translation systems.",
        "dcterms:title": "IWSTL Development and Test Data",
        "dcterms:issued": "",
        "dcterms:language": "",
        "dcterms:identifier": "",
        "dcat:theme": [
            "Machine Translation"
        ],
        "dcat:keyword": [
            "Development data",
            "Test data",
            "Machine translation evaluation"
        ],
        "dcat:landingPage": "",
        "dcterms:hasVersion": "",
        "dcterms:format": "",
        "mls:task": []
    }
]