[
    {
        "dcterms:creator": [
            "Timo Sztyler",
            "Heiner Stuckenschmidt",
            "Wolfgang Petrich"
        ],
        "dcterms:description": "This dataset consists of tracking Activities of Daily Living (ADLs) performed by seven individuals in an IoT-based smart home environment over a period of 14 days, capturing multiple occurrences of different ADLs using wireless and wearable sensors.",
        "dcterms:title": "Sztyler et al. Dataset",
        "dcterms:issued": "2017",
        "dcterms:language": "",
        "dcterms:identifier": "",
        "dcat:theme": [
            "Activity Recognition",
            "Smart Home"
        ],
        "dcat:keyword": [
            "ADLs",
            "IoT",
            "Wearable Sensors",
            "Activity Tracking"
        ],
        "dcat:landingPage": "",
        "dcterms:hasVersion": "",
        "dcterms:format": "",
        "mls:task": [
            "Activity Recognition"
        ]
    },
    {
        "dcterms:creator": [
            "I Goodfellow",
            "D Erhan",
            "PL Carrier",
            "A Courville",
            "M Mirza",
            "B Hamner",
            "W Cukierski",
            "Y Tang",
            "DH Lee",
            "Y Zhou",
            "C Ramaiah",
            "F Feng",
            "R Li",
            "X Wang",
            "D Athanasakis",
            "J Shawe-Taylor",
            "M Milakov",
            "J Park",
            "R Ionescu",
            "M Popescu",
            "C Grozea",
            "J Bergstra",
            "J Xie",
            "L Romaszko",
            "B Xu",
            "Z Chuang"
        ],
        "dcterms:description": "This dataset consists of facial images of users captured while they performed different activities, providing information about muscle movements and associated emotional states using the Facial Action Coding System (FACS).",
        "dcterms:title": "Goodfellow et al. Dataset",
        "dcterms:issued": "2013",
        "dcterms:language": "",
        "dcterms:identifier": "",
        "dcat:theme": [
            "Facial Emotion Recognition",
            "Machine Learning"
        ],
        "dcat:keyword": [
            "Facial Images",
            "Emotion Analysis",
            "FACS",
            "Machine Learning"
        ],
        "dcat:landingPage": "",
        "dcterms:hasVersion": "",
        "dcterms:format": "",
        "mls:task": [
            "Emotion Recognition"
        ]
    },
    {
        "dcterms:creator": [
            "K. Jack",
            "K. William"
        ],
        "dcterms:description": "The UK-DALE dataset consists of domestic appliance-level electricity demand and whole house demand data from five UK homes, recorded over a time resolution of six seconds from 2012 to 2015.",
        "dcterms:title": "UK Domestic Appliance Level Electricity (DALE) Dataset",
        "dcterms:issued": "2015",
        "dcterms:language": "",
        "dcterms:identifier": "",
        "dcat:theme": [
            "Energy Consumption",
            "Smart Home"
        ],
        "dcat:keyword": [
            "Electricity Demand",
            "Smart Homes",
            "Appliance Usage",
            "Energy Monitoring"
        ],
        "dcat:landingPage": "",
        "dcterms:hasVersion": "",
        "dcterms:format": "",
        "mls:task": [
            "Energy Analysis"
        ]
    }
]