[
    {
        "dcterms:creator": [
            "P. Sen",
            "G. Namata",
            "M. Bilgic",
            "L. Getoor",
            "B. Galligher",
            "T. Eliassi-Rad"
        ],
        "dcterms:description": "A citation network dataset used for benchmarking node classification algorithms, where nodes represent documents and edges represent links among these documents.",
        "dcterms:title": "Cora",
        "dcterms:issued": "2008",
        "dcterms:language": "",
        "dcterms:identifier": "",
        "dcat:theme": [
            "Graph Data",
            "Node Classification"
        ],
        "dcat:keyword": [
            "Citation network",
            "Node classification",
            "Graph Convolutional Networks"
        ],
        "dcat:landingPage": "",
        "dcterms:hasVersion": "",
        "dcterms:format": "Graph",
        "mls:task": [
            "Node Classification"
        ]
    },
    {
        "dcterms:creator": [
            "P. Sen",
            "G. Namata",
            "M. Bilgic",
            "L. Getoor",
            "B. Galligher",
            "T. Eliassi-Rad"
        ],
        "dcterms:description": "A citation network dataset used for benchmarking node classification algorithms, where nodes represent documents and edges represent links among these documents.",
        "dcterms:title": "CiteSeer",
        "dcterms:issued": "2008",
        "dcterms:language": "",
        "dcterms:identifier": "",
        "dcat:theme": [
            "Graph Data",
            "Node Classification"
        ],
        "dcat:keyword": [
            "Citation network",
            "Node classification",
            "Graph Convolutional Networks"
        ],
        "dcat:landingPage": "",
        "dcterms:hasVersion": "",
        "dcterms:format": "Graph",
        "mls:task": [
            "Node Classification"
        ]
    },
    {
        "dcterms:creator": [
            "P. Sen",
            "G. Namata",
            "M. Bilgic",
            "L. Getoor",
            "B. Galligher",
            "T. Eliassi-Rad"
        ],
        "dcterms:description": "A citation network dataset used for benchmarking node classification algorithms, where nodes represent documents and edges represent links among these documents.",
        "dcterms:title": "PubMed",
        "dcterms:issued": "2008",
        "dcterms:language": "",
        "dcterms:identifier": "",
        "dcat:theme": [
            "Graph Data",
            "Node Classification"
        ],
        "dcat:keyword": [
            "Citation network",
            "Node classification",
            "Graph Convolutional Networks"
        ],
        "dcat:landingPage": "",
        "dcterms:hasVersion": "",
        "dcterms:format": "Graph",
        "mls:task": [
            "Node Classification"
        ]
    }
]