[
    {
        "dcterms:creator": [
            "K. M. Hermann",
            "T. Kocisky",
            "E. Grefenstette",
            "L. Espeholt",
            "W. Kay",
            "M. Suleyman",
            "P. Blunsom"
        ],
        "dcterms:description": "A dataset used for training and evaluating extractive summarization models, consisting of news articles and their corresponding summaries.",
        "dcterms:title": "CNNDM",
        "dcterms:issued": "2015",
        "dcterms:language": "",
        "dcterms:identifier": "",
        "dcat:theme": [
            "Text Summarization",
            "Natural Language Processing"
        ],
        "dcat:keyword": [
            "Extractive Summarization",
            "News Articles",
            "Summarization Benchmark"
        ],
        "dcat:landingPage": "",
        "dcterms:hasVersion": "",
        "dcterms:format": "Text",
        "mls:task": [
            "Extractive Summarization"
        ]
    },
    {
        "dcterms:creator": [
            "E. Sandhaus"
        ],
        "dcterms:description": "The New York Times Annotated Corpus, a dataset containing articles from the New York Times along with annotations for various linguistic features.",
        "dcterms:title": "NYT",
        "dcterms:issued": "2008",
        "dcterms:language": "",
        "dcterms:identifier": "",
        "dcat:theme": [
            "Text Summarization",
            "Natural Language Processing"
        ],
        "dcat:keyword": [
            "Annotated Corpus",
            "News Articles",
            "Summarization Benchmark"
        ],
        "dcat:landingPage": "",
        "dcterms:hasVersion": "",
        "dcterms:format": "Text",
        "mls:task": [
            "Extractive Summarization"
        ]
    }
]