[
    {
        "dcterms:creator": [
            "D. Anicic",
            "S. Rudolph",
            "P. Fodor",
            "N. Stojanovic"
        ],
        "dcterms:description": "A framework for stream reasoning and complex event processing.",
        "dcterms:title": "EVOLP",
        "dcterms:issued": "2012",
        "dcterms:language": "",
        "dcterms:identifier": "",
        "dcat:theme": [],
        "dcat:keyword": [
            "Stream reasoning",
            "Complex event processing"
        ],
        "dcat:landingPage": "",
        "dcterms:hasVersion": "",
        "dcterms:format": "",
        "mls:task": []
    },
    {
        "dcterms:creator": [
            "D. Barbieri",
            "D. Braga",
            "S. Ceri",
            "E. Valle",
            "M. Grossniklaus"
        ],
        "dcterms:description": "A continuous query language designed for RDF data streams.",
        "dcterms:title": "C-SPARQL",
        "dcterms:issued": "2010",
        "dcterms:language": "",
        "dcterms:identifier": "",
        "dcat:theme": [],
        "dcat:keyword": [
            "Continuous queries",
            "RDF data streams"
        ],
        "dcat:landingPage": "",
        "dcterms:hasVersion": "",
        "dcterms:format": "",
        "mls:task": []
    },
    {
        "dcterms:creator": [
            "D. Anicic",
            "S. Rudolph",
            "P. Fodor",
            "N. Stojanovic"
        ],
        "dcterms:description": "A framework for stream reasoning and complex event processing.",
        "dcterms:title": "ETALIS",
        "dcterms:issued": "2012",
        "dcterms:language": "",
        "dcterms:identifier": "",
        "dcat:theme": [],
        "dcat:keyword": [
            "Stream reasoning",
            "Complex event processing"
        ],
        "dcat:landingPage": "",
        "dcterms:hasVersion": "",
        "dcterms:format": "",
        "mls:task": []
    },
    {
        "dcterms:creator": [
            "M. Homola",
            "M. Knorr",
            "J. Leite",
            "M. Slota"
        ],
        "dcterms:description": "Knowledge bases that integrate multiple contexts in a multi-context system.",
        "dcterms:title": "MKNF knowledge bases",
        "dcterms:issued": "2012",
        "dcterms:language": "",
        "dcterms:identifier": "",
        "dcat:theme": [],
        "dcat:keyword": [
            "Multi-context systems",
            "Knowledge bases"
        ],
        "dcat:landingPage": "",
        "dcterms:hasVersion": "",
        "dcterms:format": "",
        "mls:task": []
    },
    {
        "dcterms:creator": [
            "M. Gebser",
            "T. Grote",
            "R. Kaminski",
            "T. Schaub"
        ],
        "dcterms:description": "A framework for reactive answer set programming.",
        "dcterms:title": "Reactive ASP",
        "dcterms:issued": "2011",
        "dcterms:language": "",
        "dcterms:identifier": "",
        "dcat:theme": [],
        "dcat:keyword": [
            "Answer set programming",
            "Reactive systems"
        ],
        "dcat:landingPage": "",
        "dcterms:hasVersion": "",
        "dcterms:format": "",
        "mls:task": []
    },
    {
        "dcterms:creator": [
            "J. Alferes",
            "A. Brogi",
            "J. Leite",
            "L. Pereira"
        ],
        "dcterms:description": "A framework for evolving logic programs.",
        "dcterms:title": "Evolving logic programs",
        "dcterms:issued": "2002",
        "dcterms:language": "",
        "dcterms:identifier": "",
        "dcat:theme": [],
        "dcat:keyword": [
            "Logic programming",
            "Evolving systems"
        ],
        "dcat:landingPage": "",
        "dcterms:hasVersion": "",
        "dcterms:format": "",
        "mls:task": []
    },
    {
        "dcterms:creator": [
            "M. Knorr",
            "M. Slota",
            "J. Leite",
            "M. Homola"
        ],
        "dcterms:description": "A framework for hybrid MKNF in multi-context systems.",
        "dcterms:title": "Hybrid MKNF",
        "dcterms:issued": "2013",
        "dcterms:language": "",
        "dcterms:identifier": "",
        "dcat:theme": [],
        "dcat:keyword": [
            "Hybrid reasoning",
            "Multi-context systems"
        ],
        "dcat:landingPage": "",
        "dcterms:hasVersion": "",
        "dcterms:format": "",
        "mls:task": []
    },
    {
        "dcterms:creator": [
            "F. Lécué",
            "J. Pan"
        ],
        "dcterms:description": "A framework for predicting knowledge in an ontology stream.",
        "dcterms:title": "Ontology Streams",
        "dcterms:issued": "2013",
        "dcterms:language": "",
        "dcterms:identifier": "",
        "dcat:theme": [],
        "dcat:keyword": [
            "Ontology",
            "Knowledge prediction"
        ],
        "dcat:landingPage": "",
        "dcterms:hasVersion": "",
        "dcterms:format": "",
        "mls:task": []
    },
    {
        "dcterms:creator": [
            "F. Roelofsen",
            "L. Serafini"
        ],
        "dcterms:description": "A study on minimal and absent information in contexts.",
        "dcterms:title": "Minimal and absent information in contexts",
        "dcterms:issued": "2005",
        "dcterms:language": "",
        "dcterms:identifier": "",
        "dcat:theme": [],
        "dcat:keyword": [
            "Information theory",
            "Contextual reasoning"
        ],
        "dcat:landingPage": "",
        "dcterms:hasVersion": "",
        "dcterms:format": "",
        "mls:task": []
    },
    {
        "dcterms:creator": [
            "Y. Wang",
            "Z. Zhuang",
            "K. Wang"
        ],
        "dcterms:description": "A study on belief change in nonmonotonic multi-context systems.",
        "dcterms:title": "Belief change in nonmonotonic multi-context systems",
        "dcterms:issued": "2013",
        "dcterms:language": "",
        "dcterms:identifier": "",
        "dcat:theme": [],
        "dcat:keyword": [
            "Belief change",
            "Nonmonotonic reasoning"
        ],
        "dcat:landingPage": "",
        "dcterms:hasVersion": "",
        "dcterms:format": "",
        "mls:task": []
    }
]