[
    {
        "dcterms:creator": [
            "T.D. Anderson"
        ],
        "dcterms:description": "The FATE study investigates the relationship between microvascular function and cardiovascular events in a cohort of firefighters, providing long-term results that highlight the predictive value of microvascular health.",
        "dcterms:title": "Firefighters and Their Endothelium (FATE) study",
        "dcterms:issued": "2011",
        "dcterms:language": "",
        "dcterms:identifier": "",
        "dcat:theme": [
            "Cardiovascular Health",
            "Microvascular Function"
        ],
        "dcat:keyword": [
            "Microvascular function",
            "Cardiovascular events",
            "Primary prevention"
        ],
        "dcat:landingPage": "",
        "dcterms:hasVersion": "",
        "dcterms:format": "",
        "mls:task": [
            "Predictive modeling",
            "Cardiovascular risk assessment"
        ]
    },
    {
        "dcterms:creator": [
            "R. Rosenberry",
            "M. D. Nelson"
        ],
        "dcterms:description": "This dataset reviews various methods for assessing reactive hyperemia, discussing its mechanisms and considerations for accurate measurement.",
        "dcterms:title": "Reactive Hyperemia",
        "dcterms:issued": "2020",
        "dcterms:language": "",
        "dcterms:identifier": "",
        "dcat:theme": [
            "Physiology",
            "Vascular Health"
        ],
        "dcat:keyword": [
            "Reactive hyperemia",
            "Measurement methods",
            "Physiological mechanisms"
        ],
        "dcat:landingPage": "",
        "dcterms:hasVersion": "",
        "dcterms:format": "",
        "mls:task": [
            "Methodological review",
            "Physiological assessment"
        ]
    },
    {
        "dcterms:creator": [
            "R. Rosenberry"
        ],
        "dcterms:description": "This dataset provides insights into age-related microvascular dysfunction using near-infrared spectroscopy, highlighting its potential as a diagnostic tool.",
        "dcterms:title": "Near-Infrared Spectroscopy (NIRS)",
        "dcterms:issued": "2018",
        "dcterms:language": "",
        "dcterms:identifier": "",
        "dcat:theme": [
            "Aging",
            "Microvascular Health"
        ],
        "dcat:keyword": [
            "Near-infrared spectroscopy",
            "Microvascular dysfunction",
            "Aging"
        ],
        "dcat:landingPage": "",
        "dcterms:hasVersion": "",
        "dcterms:format": "",
        "mls:task": [
            "Diagnostic assessment",
            "Aging research"
        ]
    },
    {
        "dcterms:creator": [
            "F.F.M. de Mul"
        ],
        "dcterms:description": "This dataset presents a physiological model for interpreting arterial spin labeling reactive hyperemia in calf muscles, providing insights into blood flow dynamics.",
        "dcterms:title": "Laser-Doppler Perfusion Monitoring",
        "dcterms:issued": "2005",
        "dcterms:language": "",
        "dcterms:identifier": "",
        "dcat:theme": [
            "Physiology",
            "Blood Flow Dynamics"
        ],
        "dcat:keyword": [
            "Laser-Doppler",
            "Perfusion monitoring",
            "Reactive hyperemia"
        ],
        "dcat:landingPage": "",
        "dcterms:hasVersion": "",
        "dcterms:format": "",
        "mls:task": [
            "Blood flow measurement",
            "Physiological modeling"
        ]
    },
    {
        "dcterms:creator": [
            "H.-J. Chen",
            "G.A. Wright"
        ],
        "dcterms:description": "This dataset focuses on a physiological model for interpreting MRI-derived microvascular reactive hyperemia, emphasizing its application in calf muscles.",
        "dcterms:title": "MRI-derived microvascular reactive hyperemia",
        "dcterms:issued": "2017",
        "dcterms:language": "",
        "dcterms:identifier": "",
        "dcat:theme": [
            "Medical Imaging",
            "Microvascular Health"
        ],
        "dcat:keyword": [
            "MRI",
            "Microvascular reactive hyperemia",
            "Calf muscles"
        ],
        "dcat:landingPage": "",
        "dcterms:hasVersion": "",
        "dcterms:format": "",
        "mls:task": [
            "Medical imaging analysis",
            "Microvascular assessment"
        ]
    }
]